workflows/__init__.py
workflows/logging.py
workflows/py.typed
workflows/contrib/__init__.py
workflows/contrib/start_service.py
workflows/contrib/status_monitor.py
workflows/frontend/__init__.py
workflows/frontend/utilization.py
workflows/recipe/README.MD
workflows/recipe/__init__.py
workflows/recipe/recipe.py
workflows/recipe/validate.py
workflows/recipe/wrapper.py
workflows/services/README.MD
workflows/services/__init__.py
workflows/services/common_service.py
workflows/services/sample_consumer.py
workflows/services/sample_pipethrough.py
workflows/services/sample_producer.py
workflows/services/sample_transaction.py
workflows/transport/__init__.py
workflows/transport/common_transport.py
workflows/transport/offline_transport.py
workflows/transport/pika_transport.py
workflows/transport/stomp_transport.py
workflows/transport/middleware/__init__.py
workflows/transport/middleware/prometheus.py
workflows/util/__init__.py
workflows/util/zocalo/README.md
workflows/util/zocalo/__init__.py
workflows/util/zocalo/configuration.py
workflows-3.2.dist-info/LICENSE
workflows-3.2.dist-info/METADATA
workflows-3.2.dist-info/WHEEL
workflows-3.2.dist-info/entry_points.txt
workflows-3.2.dist-info/top_level.txt
workflows-3.2.dist-info/RECORD
