Metadata-Version: 2.2
Name: workflows
Version: 3.2
Summary: Data processing in distributed environments
Author-email: Diamond Light Source <scientificsoftware@diamond.ac.uk>
License: BSD-3-Clause
Project-URL: Download, https://github.com/DiamondLightSource/python-workflows/releases
Project-URL: Documentation, https://github.com/DiamondLightSource/python-workflows
Project-URL: GitHub, https://github.com/DiamondLightSource/python-workflows
Project-URL: Bug-Tracker, https://github.com/DiamondLightSource/python-workflows/issues
Classifier: Development Status :: 5 - Production/Stable
Classifier: Intended Audience :: Developers
Classifier: License :: OSI Approved :: BSD License
Classifier: Programming Language :: Python :: 3
Classifier: Operating System :: OS Independent
Classifier: Topic :: Software Development :: Libraries :: Python Modules
Requires-Python: >=3.10
License-File: LICENSE
Requires-Dist: bidict
Requires-Dist: pika
Requires-Dist: setuptools
Requires-Dist: stomp-py>=7
Provides-Extra: prometheus
Requires-Dist: prometheus-client; extra == "prometheus"
